{
  "lang": "English",
  "title": "理想的なステイをしよう!! – ニセコセントラル",
  "login": "ログイン",
  "createAccount": "サインアップ",
  "header": {
    "navMenu": [
      ["会社概要", "/about"],
      ["ブログ", "/blog"],
      ["ニセコ", "/niseko"],
      ["ライブカメラ", "/live"],
      ["天気", "/weather"]
    ],
    "specialMenu": [
      ["宿泊施設", "/"],
      ["ロングステイ", "/long-stay"],
      ["お得情報", "/special-deals"],
      ["サービス", "/guest-service"],
      ["Q&A", "/faq"],
      ["お問い合わせ", "/contact"]
    ],
    "menu": "メニュー",
    "mobileMenu": [
      ["宿泊施設", "/"],
      ["お得情報", "/special-deals"],
      ["サービス", "/guest-service"],
      ["Q&A", "/faq"],
      ["会社概要", "/about"],
      ["ブログ", "/blog"],
      ["ニセコ", "/niseko"],
      ["天気", "/weather"],
      ["お問い合わせ", "/contact"],
      ["サインアップ", "/signup"],
      ["ログイン", "/login"]
    ]
  },
  "footer": {
    "terms": "利用規約",
    "privacy": "プライバシーポリシー",
    "menus": [
      [
        "宿泊施設",
        "お客様の声",
        "Q&A",
        "エクスプレスチェックイン",
        "地図",
        "投資する"
      ],
      [
        "サービス",
        "転送",
        "コンシェルジュ",
        "冬季サービス",
        "夏のサービス",
        "ニセコ体験パスポート"
      ],
      [
        "会社概要",
        "私たちのチーム",
        "キャリア",
        "管理",
        "エージェント",
        "オーナー",
        "グループ"
      ],
      ["ブログ", "ニセコ", "ライブ", "天気"]
    ],
    "newsletter": {
      "title": "メーリングリストにご参加ください!",
      "subtitle": "限定オファー、特別セールのニュースなどを入手しましょう! *すべてのフィールドが必須です。",
      "subscribe": "購読する",
      "given_name": "名",
      "full_name": "フルネーム",
      "email": "メール"
    }
  },
  "stay_dates_and_filters": "滞在日とフィルター",
  "stay_label": "滞在日",
  "nights": "泊",
  "guests": "ゲスト",
  "adults": "大人",
  "children": "子供",
  "infants": "赤ちゃん",
  "price_range": "価格帯",
  "room_type": "部屋タイプ",
  "room_options": [
    "スタジオルーム",
    "スタジオアパートメント",
    "1ベッドルーム",
    "2ベッドルーム」",
    "2ベッドルームペントハウス",
    "3ベッドルーム",
    "3ベッドルームペントハウス",
    "4ベッドルーム",
    "5ベッドルーム"
  ],
  "find_accomodation_label": "宿泊施設名を検索",
  "accomodation_placeholder": "キーワードを入力してください",
  "booking_card": {
    "see_more": "もっと見る",
    "floor_plan": "フロアプラン"
  }
}
